brain_games/__init__.py
brain_games/cli.py
brain_games/game_engine.py
brain_games/games/__init__.py
brain_games/games/brain_calc.py
brain_games/games/brain_even.py
brain_games/games/brain_gcd.py
brain_games/games/brain_prime.py
brain_games/games/brain_progression.py
brain_games/scripts/__init__.py
brain_games/scripts/brain_calc.py
brain_games/scripts/brain_even.py
brain_games/scripts/brain_games.py
brain_games/scripts/brain_gcd.py
brain_games/scripts/brain_prime.py
brain_games/scripts/brain_progression.py
pengue_brain_games-0.1.1.dist-info/METADATA
pengue_brain_games-0.1.1.dist-info/WHEEL
pengue_brain_games-0.1.1.dist-info/entry_points.txt
pengue_brain_games-0.1.1.dist-info/RECORD
